dvsholog/__init__.py
dvsholog/aperture.py
dvsholog/beam.py
dvsholog/c_code.c
dvsholog/c_code.cpython-312-darwin.so
dvsholog/c_code.h
dvsholog/cffi_code.py
dvsholog/dataset.py
dvsholog/flag.py
dvsholog/hologreport.py
dvsholog/utilities.py
dvsholog-0.0.1.dist-info/licenses/LICENSE
dvsholog-0.0.1.dist-info/METADATA
dvsholog-0.0.1.dist-info/WHEEL
dvsholog-0.0.1.dist-info/top_level.txt
dvsholog-0.0.1.dist-info/RECORD
